<?xml version="1.0" encoding="UTF-8"?>
<export version="D">
  <design>
    <source>/home/lukas/Arduino/sketch_oct26a/schema/teddy/teddy.sch</source>
    <date>So 01 Nov 2020 14:15:46</date>
    <tool>Eeschema 5.1.5+dfsg1-2build2</tool>
    <sheet number="1" name="/" tstamps="/">
      <title_block>
        <title/>
        <company/>
        <rev/>
        <date/>
        <source>teddy.sch</source>
        <comment number="1" value=""/>
        <comment number="2" value=""/>
        <comment number="3" value=""/>
        <comment number="4" value=""/>
      </title_block>
    </sheet>
  </design>
  <components>
    <comp ref="U1">
      <value>ESP-12E</value>
      <datasheet>http://l0l.org.uk/2014/12/esp8266-modules-hardware-guide-gotta-catch-em-all/</datasheet>
      <libsource lib="esp8266" part="ESP-12E" description="ESP8266 ESP-12E module, 22 pins, 2mm, PCB antenna"/>
      <sheetpath names="/" tstamps="/"/>
      <tstamp>5F9EB9E3</tstamp>
    </comp>
    <comp ref="Q1">
      <value>BC547</value>
      <footprint>Package_TO_SOT_THT:TO-92_Inline</footprint>
      <datasheet>http://www.fairchildsemi.com/ds/BC/BC547.pdf</datasheet>
      <libsource lib="Transistor_BJT" part="BC547" description="0.1A Ic, 45V Vce, Small Signal NPN Transistor, TO-92"/>
      <sheetpath names="/" tstamps="/"/>
      <tstamp>5F9F142A</tstamp>
    </comp>
    <comp ref="LS1">
      <value>Speaker</value>
      <datasheet>~</datasheet>
      <libsource lib="Device" part="Speaker" description="Speaker"/>
      <sheetpath names="/" tstamps="/"/>
      <tstamp>5F9F2EAD</tstamp>
    </comp>
    <comp ref="R5">
      <value>1k</value>
      <datasheet>~</datasheet>
      <libsource lib="Device" part="R" description="Resistor"/>
      <sheetpath names="/" tstamps="/"/>
      <tstamp>5F9F3D89</tstamp>
    </comp>
    <comp ref="J1">
      <value>Conn_01x04_Male</value>
      <datasheet>~</datasheet>
      <libsource lib="Connector" part="Conn_01x04_Male" description="Generic connector, single row, 01x04, script generated (kicad-library-utils/schlib/autogen/connector/)"/>
      <sheetpath names="/" tstamps="/"/>
      <tstamp>5F9FC3C9</tstamp>
    </comp>
    <comp ref="Flash1">
      <value>SW_Push</value>
      <datasheet>~</datasheet>
      <libsource lib="Switch" part="SW_Push" description="Push button switch, generic, two pins"/>
      <sheetpath names="/" tstamps="/"/>
      <tstamp>5FA046C3</tstamp>
    </comp>
    <comp ref="Reset1">
      <value>SW_Push</value>
      <datasheet>~</datasheet>
      <libsource lib="Switch" part="SW_Push" description="Push button switch, generic, two pins"/>
      <sheetpath names="/" tstamps="/"/>
      <tstamp>5FA0F0FA</tstamp>
    </comp>
    <comp ref="BellyBig1">
      <value>SW_Push</value>
      <datasheet>~</datasheet>
      <libsource lib="Switch" part="SW_Push" description="Push button switch, generic, two pins"/>
      <sheetpath names="/" tstamps="/"/>
      <tstamp>5FA0F82A</tstamp>
    </comp>
    <comp ref="R2">
      <value>1k</value>
      <datasheet>~</datasheet>
      <libsource lib="Device" part="R" description="Resistor"/>
      <sheetpath names="/" tstamps="/"/>
      <tstamp>5FA10F04</tstamp>
    </comp>
    <comp ref="R1">
      <value>1k</value>
      <datasheet>~</datasheet>
      <libsource lib="Device" part="R" description="Resistor"/>
      <sheetpath names="/" tstamps="/"/>
      <tstamp>5FA15D93</tstamp>
    </comp>
    <comp ref="R3">
      <value>1k</value>
      <datasheet>~</datasheet>
      <libsource lib="Device" part="R" description="Resistor"/>
      <sheetpath names="/" tstamps="/"/>
      <tstamp>5FA289F2</tstamp>
    </comp>
    <comp ref="BellySmall1">
      <value>SW_Push</value>
      <datasheet>~</datasheet>
      <libsource lib="Switch" part="SW_Push" description="Push button switch, generic, two pins"/>
      <sheetpath names="/" tstamps="/"/>
      <tstamp>5FA3CB74</tstamp>
    </comp>
    <comp ref="R4">
      <value>1k</value>
      <datasheet>~</datasheet>
      <libsource lib="Device" part="R" description="Resistor"/>
      <sheetpath names="/" tstamps="/"/>
      <tstamp>5FA3CB80</tstamp>
    </comp>
    <comp ref="J2">
      <value>Conn_01x02_Male</value>
      <datasheet>~</datasheet>
      <libsource lib="Connector" part="Conn_01x02_Male" description="Generic connector, single row, 01x02, script generated (kicad-library-utils/schlib/autogen/connector/)"/>
      <sheetpath names="/" tstamps="/"/>
      <tstamp>5FA4238A</tstamp>
    </comp>
    <comp ref="J3">
      <value>Conn_01x03_Male</value>
      <datasheet>~</datasheet>
      <libsource lib="Connector" part="Conn_01x03_Male" description="Generic connector, single row, 01x03, script generated (kicad-library-utils/schlib/autogen/connector/)"/>
      <sheetpath names="/" tstamps="/"/>
      <tstamp>5FA4342D</tstamp>
    </comp>
    <comp ref="J4">
      <value>Conn_01x02_Male</value>
      <datasheet>~</datasheet>
      <libsource lib="Connector" part="Conn_01x02_Male" description="Generic connector, single row, 01x02, script generated (kicad-library-utils/schlib/autogen/connector/)"/>
      <sheetpath names="/" tstamps="/"/>
      <tstamp>5FA53531</tstamp>
    </comp>
  </components>
  <libparts>
    <libpart lib="Connector" part="Conn_01x02_Male">
      <description>Generic connector, single row, 01x02, script generated (kicad-library-utils/schlib/autogen/connector/)</description>
      <docs>~</docs>
      <footprints>
        <fp>Connector*:*_1x??_*</fp>
      </footprints>
      <fields>
        <field name="Reference">J</field>
        <field name="Value">Conn_01x02_Male</field>
      </fields>
      <pins>
        <pin num="1" name="Pin_1" type="passive"/>
        <pin num="2" name="Pin_2" type="passive"/>
      </pins>
    </libpart>
    <libpart lib="Connector" part="Conn_01x03_Male">
      <description>Generic connector, single row, 01x03, script generated (kicad-library-utils/schlib/autogen/connector/)</description>
      <docs>~</docs>
      <footprints>
        <fp>Connector*:*_1x??_*</fp>
      </footprints>
      <fields>
        <field name="Reference">J</field>
        <field name="Value">Conn_01x03_Male</field>
      </fields>
      <pins>
        <pin num="1" name="Pin_1" type="passive"/>
        <pin num="2" name="Pin_2" type="passive"/>
        <pin num="3" name="Pin_3" type="passive"/>
      </pins>
    </libpart>
    <libpart lib="Connector" part="Conn_01x04_Male">
      <description>Generic connector, single row, 01x04, script generated (kicad-library-utils/schlib/autogen/connector/)</description>
      <docs>~</docs>
      <footprints>
        <fp>Connector*:*_1x??_*</fp>
      </footprints>
      <fields>
        <field name="Reference">J</field>
        <field name="Value">Conn_01x04_Male</field>
      </fields>
      <pins>
        <pin num="1" name="Pin_1" type="passive"/>
        <pin num="2" name="Pin_2" type="passive"/>
        <pin num="3" name="Pin_3" type="passive"/>
        <pin num="4" name="Pin_4" type="passive"/>
      </pins>
    </libpart>
    <libpart lib="Device" part="R">
      <description>Resistor</description>
      <docs>~</docs>
      <footprints>
        <fp>R_*</fp>
      </footprints>
      <fields>
        <field name="Reference">R</field>
        <field name="Value">R</field>
      </fields>
      <pins>
        <pin num="1" name="~" type="passive"/>
        <pin num="2" name="~" type="passive"/>
      </pins>
    </libpart>
    <libpart lib="Device" part="Speaker">
      <description>Speaker</description>
      <docs>~</docs>
      <fields>
        <field name="Reference">LS</field>
        <field name="Value">Speaker</field>
      </fields>
      <pins>
        <pin num="1" name="1" type="input"/>
        <pin num="2" name="2" type="input"/>
      </pins>
    </libpart>
    <libpart lib="Switch" part="SW_Push">
      <description>Push button switch, generic, two pins</description>
      <docs>~</docs>
      <fields>
        <field name="Reference">SW</field>
        <field name="Value">SW_Push</field>
      </fields>
      <pins>
        <pin num="1" name="1" type="passive"/>
        <pin num="2" name="2" type="passive"/>
      </pins>
    </libpart>
    <libpart lib="Transistor_BJT" part="BC547">
      <aliases>
        <alias>BC546</alias>
        <alias>BC548</alias>
        <alias>BC549</alias>
        <alias>BC550</alias>
        <alias>BC337</alias>
        <alias>BC338</alias>
      </aliases>
      <description>0.1A Ic, 45V Vce, Small Signal NPN Transistor, TO-92</description>
      <docs>http://www.fairchildsemi.com/ds/BC/BC547.pdf</docs>
      <footprints>
        <fp>TO?92*</fp>
      </footprints>
      <fields>
        <field name="Reference">Q</field>
        <field name="Value">BC547</field>
        <field name="Footprint">Package_TO_SOT_THT:TO-92_Inline</field>
      </fields>
      <pins>
        <pin num="1" name="C" type="passive"/>
        <pin num="2" name="B" type="input"/>
        <pin num="3" name="E" type="passive"/>
      </pins>
    </libpart>
    <libpart lib="esp8266" part="ESP-12E">
      <aliases>
        <alias>ESP-12F</alias>
      </aliases>
      <description>ESP8266 ESP-12E module, 22 pins, 2mm, PCB antenna</description>
      <docs>http://l0l.org.uk/2014/12/esp8266-modules-hardware-guide-gotta-catch-em-all/</docs>
      <footprints>
        <fp>ESP-12E</fp>
        <fp>ESP-12E_SMD</fp>
      </footprints>
      <fields>
        <field name="Reference">U</field>
        <field name="Value">ESP-12E</field>
      </fields>
      <pins>
        <pin num="1" name="REST" type="input"/>
        <pin num="2" name="ADC" type="passive"/>
        <pin num="3" name="CH_PD" type="input"/>
        <pin num="4" name="GPIO16" type="BiDi"/>
        <pin num="5" name="GPIO14" type="BiDi"/>
        <pin num="6" name="GPIO12" type="BiDi"/>
        <pin num="7" name="GPIO13" type="BiDi"/>
        <pin num="8" name="VCC" type="power_in"/>
        <pin num="9" name="GND" type="power_in"/>
        <pin num="10" name="GPIO15" type="BiDi"/>
        <pin num="11" name="GPIO2" type="BiDi"/>
        <pin num="12" name="GPIO0" type="BiDi"/>
        <pin num="13" name="GPIO4" type="BiDi"/>
        <pin num="14" name="GPIO5" type="BiDi"/>
        <pin num="15" name="RXD" type="input"/>
        <pin num="16" name="TXD" type="output"/>
        <pin num="17" name="CS0" type="BiDi"/>
        <pin num="18" name="MISO" type="BiDi"/>
        <pin num="19" name="GPIO9" type="BiDi"/>
        <pin num="20" name="GPIO10" type="BiDi"/>
        <pin num="21" name="MOSI" type="BiDi"/>
        <pin num="22" name="SCLK" type="BiDi"/>
      </pins>
    </libpart>
  </libparts>
  <libraries>
    <library logical="Connector">
      <uri>/usr/share/kicad/library/Connector.lib</uri>
    </library>
    <library logical="Device">
      <uri>/usr/share/kicad/library/Device.lib</uri>
    </library>
    <library logical="Switch">
      <uri>/usr/share/kicad/library/Switch.lib</uri>
    </library>
    <library logical="Transistor_BJT">
      <uri>/usr/share/kicad/library/Transistor_BJT.lib</uri>
    </library>
    <library logical="esp8266">
      <uri>/home/lukas/kicad/libraries/kicad-ESP8266/ESP8266.lib</uri>
    </library>
  </libraries>
  <nets>
    <net code="1" name="/BELLY_BIG">
      <node ref="BellyBig1" pin="2"/>
      <node ref="R3" pin="1"/>
    </net>
    <net code="2" name="GND">
      <node ref="J4" pin="1"/>
      <node ref="J1" pin="1"/>
      <node ref="BellyBig1" pin="1"/>
      <node ref="J3" pin="1"/>
      <node ref="Reset1" pin="1"/>
      <node ref="Flash1" pin="1"/>
      <node ref="U1" pin="9"/>
      <node ref="Q1" pin="3"/>
      <node ref="BellySmall1" pin="1"/>
    </net>
    <net code="3" name="+3V3">
      <node ref="R2" pin="2"/>
      <node ref="R3" pin="2"/>
      <node ref="U1" pin="8"/>
      <node ref="R1" pin="2"/>
      <node ref="R4" pin="2"/>
    </net>
    <net code="4" name="/FLASH">
      <node ref="U1" pin="12"/>
      <node ref="Flash1" pin="2"/>
      <node ref="R1" pin="1"/>
    </net>
    <net code="5" name="/BELLY_SMALL">
      <node ref="R4" pin="1"/>
      <node ref="BellySmall1" pin="2"/>
    </net>
    <net code="6" name="/RST">
      <node ref="R2" pin="1"/>
      <node ref="Reset1" pin="2"/>
      <node ref="U1" pin="1"/>
    </net>
    <net code="7" name="/SPK_OUT">
      <node ref="LS1" pin="2"/>
      <node ref="Q1" pin="1"/>
      <node ref="J2" pin="1"/>
    </net>
    <net code="8" name="+5V">
      <node ref="J3" pin="3"/>
      <node ref="J2" pin="2"/>
      <node ref="J4" pin="2"/>
      <node ref="J1" pin="4"/>
      <node ref="LS1" pin="1"/>
    </net>
    <net code="9" name="Net-(J3-Pad2)">
      <node ref="J3" pin="2"/>
    </net>
    <net code="10" name="Net-(U1-Pad22)">
      <node ref="U1" pin="22"/>
    </net>
    <net code="11" name="Net-(U1-Pad13)">
      <node ref="U1" pin="13"/>
    </net>
    <net code="12" name="Net-(U1-Pad14)">
      <node ref="U1" pin="14"/>
    </net>
    <net code="13" name="/TX">
      <node ref="U1" pin="16"/>
      <node ref="J1" pin="2"/>
    </net>
    <net code="14" name="Net-(U1-Pad17)">
      <node ref="U1" pin="17"/>
    </net>
    <net code="15" name="Net-(U1-Pad18)">
      <node ref="U1" pin="18"/>
    </net>
    <net code="16" name="Net-(U1-Pad19)">
      <node ref="U1" pin="19"/>
    </net>
    <net code="17" name="Net-(Q1-Pad2)">
      <node ref="R5" pin="1"/>
      <node ref="Q1" pin="2"/>
    </net>
    <net code="18" name="Net-(U1-Pad6)">
      <node ref="U1" pin="6"/>
    </net>
    <net code="19" name="Net-(U1-Pad2)">
      <node ref="U1" pin="2"/>
    </net>
    <net code="20" name="Net-(U1-Pad3)">
      <node ref="U1" pin="3"/>
    </net>
    <net code="21" name="Net-(U1-Pad4)">
      <node ref="U1" pin="4"/>
    </net>
    <net code="22" name="Net-(U1-Pad5)">
      <node ref="U1" pin="5"/>
    </net>
    <net code="23" name="Net-(U1-Pad7)">
      <node ref="U1" pin="7"/>
    </net>
    <net code="24" name="Net-(U1-Pad10)">
      <node ref="U1" pin="10"/>
    </net>
    <net code="25" name="Net-(U1-Pad20)">
      <node ref="U1" pin="20"/>
    </net>
    <net code="26" name="Net-(U1-Pad11)">
      <node ref="U1" pin="11"/>
    </net>
    <net code="27" name="Net-(U1-Pad21)">
      <node ref="U1" pin="21"/>
    </net>
    <net code="28" name="/RX">
      <node ref="U1" pin="15"/>
      <node ref="J1" pin="3"/>
      <node ref="R5" pin="2"/>
    </net>
  </nets>
</export>
